skembeddings/__init__.py
skembeddings/_hub.py
skembeddings/base.py
skembeddings/error.py
skembeddings/models/__init__.py
skembeddings/models/doc2vec.py
skembeddings/models/glove.py
skembeddings/models/word2vec.py
skembeddings/pipeline.py
skembeddings/tokenizers/__init__.py
skembeddings/tokenizers/_huggingface.py
skembeddings/utils.py
scikit_embeddings-0.3.1.dist-info/METADATA
scikit_embeddings-0.3.1.dist-info/WHEEL
scikit_embeddings-0.3.1.dist-info/LICENSE
scikit_embeddings-0.3.1.dist-info/RECORD
