Metadata-Version: 2.1
Name: scikit-embeddings
Version: 0.3.1
Summary: Tools for training word and document embeddings in scikit-learn.
License: MIT
Author: Márton Kardos
Author-email: power.up1163@gmail.com
Requires-Python: >=3.9,<4.0
Classifier: License :: OSI Approved :: MIT License
Classifier: Programming Language :: Python :: 3
Classifier: Programming Language :: Python :: 3.9
Classifier: Programming Language :: Python :: 3.10
Classifier: Programming Language :: Python :: 3.11
Provides-Extra: glove
Provides-Extra: spacy
Requires-Dist: catalogue (>=2.0.8,<3.0.0)
Requires-Dist: confection (>=0.1.0,<0.2.0)
Requires-Dist: gensim (>=4.3.0,<5.0.0)
Requires-Dist: glovpy (>=0.1.0,<0.2.0) ; extra == "glove"
Requires-Dist: huggingface-hub (>=0.16.0,<0.17.0)
Requires-Dist: scikit-learn (>=1.2.0,<2.0.0)
Requires-Dist: tokenizers (>=0.13.0,<0.14.0)
